fastero/__init__.py
fastero/__main__.py
fastero/core.py
fastero/exporter.py
fastero/utils.py
fastero-0.2.5.dist-info/LICENSE
fastero-0.2.5.dist-info/METADATA
fastero-0.2.5.dist-info/WHEEL
fastero-0.2.5.dist-info/entry_points.txt
fastero-0.2.5.dist-info/top_level.txt
fastero-0.2.5.dist-info/RECORD
