Metadata-Version: 2.1
Name: fastero
Version: 0.2.5
Summary: Python timeit CLI for the 21st century.
Home-page: https://fastero.readthedocs.io
Author: Wasi Master
Author-email: arianmollik323@gmail.com
License: MIT
Project-URL: Bug Tracker, https://github.com/wasi-master/fastero/issues
Project-URL: Source, https://github.com/wasi-master/fastero
Project-URL: Documentation, https://fastero.readthedocs.io
Project-URL: Say Thanks, https://saythanks.io/to/wasi-master
Keywords: timeit,fastero,hyperfine
Platform: UNKNOWN
Classifier: Development Status :: 4 - Beta
Classifier: Environment :: Console
Classifier: Intended Audience :: Developers
Classifier: Intended Audience :: End Users/Desktop
Classifier: License :: OSI Approved :: MIT License
Classifier: Natural Language :: English
Classifier: Operating System :: OS Independent
Classifier: Programming Language :: Python :: 3
Classifier: Programming Language :: Python :: 3 :: Only
Classifier: Programming Language :: Python :: 3.6
Classifier: Programming Language :: Python :: 3.7
Classifier: Programming Language :: Python :: 3.8
Classifier: Programming Language :: Python :: 3.9
Classifier: Programming Language :: Python :: 3.10
Classifier: Topic :: Terminals
Requires-Python: >=3.7
License-File: LICENSE
Requires-Dist: rich (==12.2.0)
Requires-Dist: click (==8.1.2)
Requires-Dist: rich-click (==1.3.0)
Requires-Dist: prompt-toolkit (==3.0.29)
Requires-Dist: ptpython (==3.0.20)
Provides-Extra: export
Requires-Dist: matplotlib ; extra == 'export'
Requires-Dist: numpy ; extra == 'export'
Requires-Dist: pyyaml ; extra == 'export'
Requires-Dist: selenium ; extra == 'export'
Requires-Dist: Pillow ; extra == 'export'
